[{"Name":"UK Drill 1","SoundId":"4766979568","UUID":1},{"Name":"Lil Darki - Year of the cap","SoundId":"4503602906","UUID":2},{"Name":"SmokePurpp - Glock in my Benz","SoundId":"3079122478","UUID":3},{"Name":"Blueface - Respect My Crippin'","SoundId":"2623442908","UUID":4},{"Name":"Ice Cube - You Know How We Do It (Instrumental)","SoundId":"3907394826","UUID":5},{"Name":"[Loud] XXXTentacion - Moon Rock","SoundId":"4769706556","UUID":6},{"Name":"XXXTentacion - YuNg BrAtZ","SoundId":"4780760021","UUID":7},{"Name":"6ix9ine - Gotti Gotti","SoundId":"2548670702","UUID":8},{"Name":"DaBaby - Surge","SoundId":"3483276733","UUID":9},{"Name":"UK Drill 2","SoundId":"4780464052","UUID":10},{"Name":"XXXTentacion - CURSE","SoundId":"4603947457","UUID":11},{"Name":"Lil Uzi Vert - Futsal Shuffle 2020","SoundId":"4508702647","UUID":12},{"Name":"Lil Uzi Vert - New Patek","SoundId":"1957356961","UUID":13},{"Name":"Lil Uzi Vert - Dark Queen","SoundId":"2674633165","UUID":14},{"Name":"Lil Uzi Vert - You Was Right","SoundId":"4634443277","UUID":15},{"Name":"Lil Uzi Vert - I'm Sorry","SoundId":"495028423","UUID":16},{"Name":"Lil Uzi Vert - I Know (Neck On Froze)","SoundId":"1868647949","UUID":17},{"Name":"Lil Uzi Vert - SO HIT","SoundId":"342142349","UUID":18},{"Name":"Lil Uzi Vert - Zoom","SoundId":"3632814573","UUID":19},{"Name":"Lil Uzi Vert - Ruler (YSL)","SoundId":"679362994","UUID":20},{"Name":"Lil Uzi Vert - Sub-Zero","SoundId":"426040431","UUID":21},{"Name":"Lil Uzi Vert - Money Longer","SoundId":"2152267962","UUID":22},{"Name":"Lil Uzi Vert - UnFazed","SoundId":"2778710314","UUID":23},{"Name":"Lil Uzi Vert - Buy It","SoundId":"3180507479","UUID":24},{"Name":"Lil Uzi Vert - XO Tour Llife3","SoundId":"1129292653","UUID":25},{"Name":"Lil Uzi Vert - Luv Scars","SoundId":"4498025902","UUID":26},{"Name":"Lil Uzi Vert - Moon Relate","SoundId":"1868647463","UUID":27},{"Name":"Lil Uzi Vert - Rollie (Bean)","SoundId":"1858545714","UUID":28},{"Name":"XXXTentacion - Ex Bitch","SoundId":"4311275450","UUID":29},{"Name":"XXXTentacion - ATTENTION!","SoundId":"4491706103","UUID":30},{"Name":"XXXTentacion - UGLY","SoundId":"4492061333","UUID":31},{"Name":"XXXTentacion - Kill My Vibe","SoundId":"4536352612","UUID":32},{"Name":"XXXTentacion - Jocelyn Flores (Edit)","SoundId":"1349382638","UUID":33},{"Name":"UK Drill 3","SoundId":"4797790743","UUID":34},{"Name":"UK Drill 4","SoundId":"4796579096","UUID":35},{"Name":"Juice WRLD - Legends","SoundId":"2198911642","UUID":36},{"Name":"21 Savage - No Heart","SoundId":"4530586343","UUID":37},{"Name":"[Loud] Monsters Inc. Theme","SoundId":"4567090901","UUID":38},{"Name":"Minecraft Parody: The Box","SoundId":"4613620329","UUID":39},{"Name":"YBN Cordae - Kung Fu","SoundId":"2087187528","UUID":40},{"Name":"Chills - Dreamland","SoundId":"2997057859","UUID":41},{"Name":"Lil Peep - Speed Gang","SoundId":"4808965714","UUID":42},{"Name":"UK Drill 5","SoundId":"4815031562","UUID":43},{"Name":"UK Drill 6","SoundId":"4814788069","UUID":44},{"Name":"scarlxrd - 6 FEET","SoundId":"1579762880","UUID":45},{"Name":"Lil Playah - Need You","SoundId":"4773039115","UUID":46},{"Name":"Dave - Streatham","SoundId":"2978826122","UUID":47},{"Name":"Dave - Funky Friday","SoundId":"3240922168","UUID":48},{"Name":"Denzel Curry - RICKY","SoundId":"3204673957","UUID":49},{"Name":"XXXTentacion - Ok Shorty!","SoundId":"3488991759","UUID":50},{"Name":"Juice WRLD - Good Days","SoundId":"3091426368","UUID":51},{"Name":"Juice WRLD - Sad","SoundId":"2112177463","UUID":52},{"Name":"YoungBoy Never Broke Again - i feel like i'm gucci mane in 2006","SoundId":"4750209135","UUID":53},{"Name":"Lil Pump - Butterfly Doors","SoundId":"2838055741","UUID":54},{"Name":"Rae Sremmurd - Swang","SoundId":"2859196159","UUID":55},{"Name":"XXXTENTACION - Off the Wall!","SoundId":"862524906","UUID":56},{"Name":"Trippie Redd - Love Scars 3","SoundId":"2696266061","UUID":57},{"Name":"Unknown T - Bop With Smoke","SoundId":"2422372052","UUID":58},{"Name":"Racist Chinese Song","SoundId":"203514210","UUID":59},{"Name":"Boneless Pizza","SoundId":"907754890","UUID":60},{"Name":"Best Cry Ever","SoundId":"436908101","UUID":61},{"Name":"DJ Keemstar - I found a Dollar","SoundId":"442120987","UUID":62},{"Name":"Juice WRLD - Lucid Dreams","SoundId":"4909156838","UUID":63},{"Name":"Juice WRLD - Legends 2","SoundId":"4532863126","UUID":64},{"Name":"What are you doing step-bro?","SoundId":"4618157210","UUID":65},{"Name":"XXXTentacion - Look At Me!","SoundId":"2833524128","UUID":66},{"Name":"Apollo fresh - Jojo Pose","SoundId":"4687362326","UUID":67},{"Name":"Lil Skies - Magic","SoundId":"4554855191","UUID":68},{"Name":"Ski Mask The Slump God - Catch Me Outside","SoundId":"4565356234","UUID":69},{"Name":"[Loud] Oliver Tree - Alien Boy","SoundId":"3763396073","UUID":70},{"Name":"6IX9INE - Billy","SoundId":"4952734000","UUID":71},{"Name":"Lil Peep - Benz Truck","SoundId":"4946521295","UUID":72},{"Name":"DevTakeFlight - Track Meet","SoundId":"5088406678","UUID":73},{"Name":"Tay K - The Race","SoundId":"5038081419","UUID":74},{"Name":"The Gummy Bear Song","SoundId":"5027800028","UUID":75},{"Name":"Juice WRLD - Let Me Know","SoundId":"5121194717","UUID":76},{"Name":"Lil Uzi Vert - Myron","SoundId":"5125262207","UUID":77},{"Name":"XXXTentacion - Sauce","SoundId":"5023758161","UUID":78},{"Name":"Tay K - I Love My Choppa","SoundId":"5142690024","UUID":79},{"Name":"Racist Song","SoundId":"5059648466","UUID":80},{"Name":"Juice WRLD - All The Girls Are The Same","SoundId":"4889478486","UUID":81},{"Name":"Trippie Redd - 6 Kiss","SoundId":"5116272104","UUID":82},{"Name":"[Loud] NWA - Fuk Da Police","SoundId":"5075772295","UUID":83},{"Name":"Pop Smoke - Dior","SoundId":"5148252464","UUID":84},{"Name":"21 Savage - Bank Account","SoundId":"5123503183","UUID":85},{"Name":"Racist Moonman Song","SoundId":"4961011336","UUID":86},{"Name":"Lil Tecca - Love No Thot","SoundId":"4042064749","UUID":87},{"Name":"Juice WRLD - Lucid Dreams","SoundId":"5090042375","UUID":88},{"Name":"XXXTentacion - YuNg BrAtZ","SoundId":"5014528212","UUID":89},{"Name":"Lil Uzi Vert - Bean (Kobe) feat. Chief Keef","SoundId":"5034720819","UUID":90},{"Name":"[Parody] Tay K - The Racist Race","SoundId":"5018921124","UUID":91},{"Name":"FREDDIE DREDD - PURE IMAGINATION","SoundId":"5151654644","UUID":92},{"Name":"Chief Keef - Faneto","SoundId":"5033740319","UUID":93},{"Name":"Comethazine x Lil Yachty - Bring That Bag Out","SoundId":"5071700663","UUID":94},{"Name":"XXXTentacion - Take a Step Back","SoundId":"5170242905","UUID":95},{"Name":"$NOT - GOSHA","SoundId":"5021316476","UUID":96},{"Name":"Aitch - Buss Down ft. ZieZie Andrewfitz","SoundId":"5224022752","UUID":97},{"Name":"KSI - Houdinini (feat. Swarmz & Tion Wayne)","SoundId":"5223679804","UUID":98},{"Name":"The Kid LAROI, Juice WRLD - GO","SoundId":"5227700106","UUID":99},{"Name":"Juice WRLD - Tell Me U lxv me ft. Trippie Red","SoundId":"5227898057","UUID":100},{"Name":"Yungster Jack - Pressure","SoundId":"5152316534","UUID":101},{"Name":"Ski Mask The Slump God - Faucet Failure","SoundId":"5184525536","UUID":102},{"Name":"Lil Uzi Vert - Top","SoundId":"5222632569","UUID":103},{"Name":"Tay-K - Coolin","SoundId":"5062678306","UUID":104},{"Name":"XXXTentacion - I'm Sippin Tea In Your hood","SoundId":"5168117214","UUID":105},{"Name":"XXXTentacion - Look At Me!","SoundId":"5149622323","UUID":106},{"Name":"Juice WRLD - Fine China","SoundId":"5191785658","UUID":107},{"Name":"21 Savage, Offset, Metro Boomin - Ric Flair Drip","SoundId":"5137562328","UUID":108},{"Name":"Juice WRLD - Armed And Dangerous","SoundId":"5189842077","UUID":109},{"Name":"21 Savage - A lot","SoundId":"4877838949","UUID":110},{"Name":"Tay K - The Race","SoundId":"5305371834","UUID":111},{"Name":"XXXTentacion - Up Like Insomniac","SoundId":"5297948943","UUID":112},{"Name":"Arabic Gummy Bear","SoundId":"5269201801","UUID":113},{"Name":"Soulja Boy Tell'em - Crank That","SoundId":"5115313929","UUID":114},{"Name":"Comethazine - Walk","SoundId":"5180529469","UUID":115},{"Name":"YBN Nahmir - Opp Stoppa","SoundId":"5180701826","UUID":116},{"Name":"6IX9INE - YAYA","SoundId":"5286069629","UUID":117},{"Name":"Lil Peep x Lil Tracy - Pain","SoundId":"4968100435","UUID":118},{"Name":"Lil Peep - Life Is Beautiful","SoundId":"5058071853","UUID":119},{"Name":"LiL PEEP - The Pull","SoundId":"5071382525","UUID":120},{"Name":"Lil Boom - Caillou","SoundId":"5297918709","UUID":121},{"Name":"Pornhub Intro","SoundId":"4795166759","UUID":122},{"Name":"Juice WRLD - Screw Juice","SoundId":"5334415549","UUID":123},{"Name":"Juice WRLD - I Want It","SoundId":"5333208161","UUID":124},{"Name":"Juice WRLD - Titanic","SoundId":"5333209375","UUID":125},{"Name":"Juice WRLD - Blood On My Jeans","SoundId":"5332846843","UUID":126},{"Name":"Juice WRLD - Conversations","SoundId":"5332841570","UUID":127},{"Name":"Juice WRLD - Bad Energy","SoundId":"5333477297","UUID":128},{"Name":"Juice WRLD - Stay High","SoundId":"5333999800","UUID":129},{"Name":"Juice WRLD - Wishing Well","SoundId":"5334124503","UUID":130},{"Name":"Lil Uzi Vert - Zoom","SoundId":"5188697892","UUID":131},{"Name":"Some Gay Parody","SoundId":"5117537523","UUID":132},{"Name":"Pop Smoke - Dior","SoundId":"4686178812","UUID":133},{"Name":"GHOSTEMANE - BONESAW","SoundId":"5295413997","UUID":134},{"Name":"LIL THRAXX - FUCK HIM FUCK HER","SoundId":"5120359296","UUID":135},{"Name":"Some Bypassed Song","SoundId":"5071506347","UUID":136},{"Name":"Pop Smoke - Foreigner","SoundId":"4950009331","UUID":137},{"Name":"Indian Barbie Girl","SoundId":"4836060763","UUID":138},{"Name":"Dkoolpharaoh - Hang Around","SoundId":"5151280610","UUID":139},{"Name":"Kodak Black - Young Prodigy","SoundId":"5175459836","UUID":140},{"Name":"Polo G - Ms Capalot","SoundId":"5243483489","UUID":141},{"Name":"G Herbo - PTSD","SoundId":"4891680088","UUID":142},{"Name":"Kodak Black - ZEZE","SoundId":"5323884648","UUID":143},{"Name":"Bobby Shmurda - Hot N*gga","SoundId":"5213409419","UUID":144},{"Name":"[Instrumental] XXXTentacion - SAD!","SoundId":"5230729556","UUID":145},{"Name":"XXXTentacion - Gospel","SoundId":"5061414047","UUID":146},{"Name":"Dr. Dre ft. Snoop Dogg - Still D.R.E.","SoundId":"5019768410","UUID":147},{"Name":"Ski Mask the Slump God - Take a Step Back","SoundId":"4966688419","UUID":148},{"Name":"Lil Yachty - 1 NIGHT","SoundId":"5196356965","UUID":149},{"Name":"Rae Sremmurd - No Type","SoundId":"4820683253","UUID":150},{"Name":"XXXTentacion - Vice City","SoundId":"4923872750","UUID":151},{"Name":"Juice WRLD - Lucid Dreams","SoundId":"3956963046","UUID":152},{"Name":"Lil Uzi Vert - XO Tour Llif3","SoundId":"4997564247","UUID":153},{"Name":"Comethazine - Hero","SoundId":"5156176694","UUID":154},{"Name":"Travis Scott - SICKO MODE ft. Drake","SoundId":"5014798229","UUID":155},{"Name":"XXXTENTACION - Teeth","SoundId":"4746927542","UUID":156},{"Name":"XXXTENTACION - Gnarly Bastard","SoundId":"4641110005","UUID":157},{"Name":"XXXTENTACION - I spoke to the devil in miami, he said everything would be fine.","SoundId":"1294908660","UUID":158},{"Name":"XXXTENTACION - Hope","SoundId":"5180520651","UUID":159},{"Name":"XXXTentacion - Revenge","SoundId":"4850637327","UUID":160},{"Name":"Juice WRLD - Tick Tock","SoundId":"5269429260","UUID":161},{"Name":"Lil Tecca - Amigo","SoundId":"5108533092","UUID":162},{"Name":"XXXTentacion - UP LIKE AN INSOMNIAC","SoundId":"5184982573","UUID":163},{"Name":"[Trap Remix] Xue Hua Piao Piao","SoundId":"5286036609","UUID":164},{"Name":"$NOT - Excuse Me","SoundId":"5160874731","UUID":165},{"Name":"$NOT - IM AT YO HOUSE","SoundId":"5248117028","UUID":166},{"Name":"Rich The Kid - Plug Walk","SoundId":"5220148870","UUID":167},{"Name":"Lil Peep & XXXTENTACION - Falling Down","SoundId":"4975899178","UUID":168},{"Name":"$NOT - Human","SoundId":"5190159589","UUID":169},{"Name":"Lil Skies - Lust","SoundId":"4905152096","UUID":170}]